.installed.cfg
.long-description.html
.mr.developer.cfg
MANIFEST.in
README.rst
bootstrap.py
buildout.cfg
development.ini
production.ini
setup.py
collective/__init__.py
collective/__init__.pyc
collective.package.egg-info/PKG-INFO
collective.package.egg-info/SOURCES.txt
collective.package.egg-info/dependency_links.txt
collective.package.egg-info/entry_points.txt
collective.package.egg-info/namespace_packages.txt
collective.package.egg-info/not-zip-safe
collective.package.egg-info/requires.txt
collective.package.egg-info/top_level.txt
collective/package/__init__.py
collective/package/configure.zcml
collective/package/install.py
collective/package/interface.py
collective/package/plugin.py
collective/package/tests.py
collective/package/version.txt
collective/package/browser/__init__.py
collective/package/browser/add_plugin.zpt
collective/package/browser/battery.png
collective/package/browser/configure.zcml
collective/package/browser/icon.gif
docs/CREDITS.txt
docs/HISTORY.txt
docs/INSTALL.txt
docs/LICENSE.GPL
docs/LICENSE.txt