Metadata-Version: 1.0
Name: collective.package
Version: 0.3.1
Summary: Sample package to demonstrate development of         add-ons for the Plone CMS
Home-page: http://collective.github.com/collective.package/
Author: Alex Clark
Author-email: aclark@aclark.net
License: ZPL
Keywords: plone example package
Platform: UNKNOWN
Classifier: Framework :: Plone
Classifier: Programming Language :: Python
Classifier: Topic :: Software Development :: Libraries :: Python Modules
